[
  {
    "id": "BK001",
    "type": "tour",
    "customerName": "John Doe",
    "customerEmail": "john.doe@email.com",
    "customerPhone": "+250 788 123 456",
    "tourId": "zambia-victoria-falls-7-day",
    "tourName": "7-Day Zambia Victoria Falls Adventure",
    "startDate": "2026-04-15",
    "endDate": "2026-04-21",
    "participants": 2,
    "totalAmount": 5760,
    "status": "confirmed",
    "createdAt": "2026-03-10T08:30:00Z",
    "notes": "Requested vegetarian meals"
  },
  {
    "id": "BK002",
    "type": "flight",
    "customerName": "Jane Smith",
    "customerEmail": "jane.smith@email.com",
    "customerPhone": "+250 788 234 567",
    "flightDetails": {
      "destination": "Dubai",
      "airline": "Qatar Airways",
      "departureDate": "2026-03-20",
      "returnDate": "2026-03-27",
      "passengers": 1,
      "class": "Economy"
    },
    "totalAmount": 599,
    "status": "pending",
    "createdAt": "2026-03-12T10:15:00Z",
    "notes": "Waiting for passport confirmation"
  },
  {
    "id": "BK003",
    "type": "tour",
    "customerName": "Mike Johnson",
    "customerEmail": "mike.j@email.com",
    "customerPhone": "+250 788 345 678",
    "tourId": "rwanda-discovery-6-day",
    "tourName": "6-Day Rwanda Discovery Package",
    "startDate": "2026-03-25",
    "endDate": "2026-03-30",
    "participants": 4,
    "totalAmount": 3100,
    "status": "confirmed",
    "createdAt": "2026-03-11T14:20:00Z",
    "notes": "Family trip with 2 children"
  },
  {
    "id": "BK004",
    "type": "apartment",
    "customerName": "Sarah Williams",
    "customerEmail": "sarah.w@email.com",
    "customerPhone": "+250 788 456 789",
    "apartmentId": "kigali-heights-luxury",
    "apartmentName": "Kigali Heights Luxury Apartment",
    "checkIn": "2026-03-18",
    "checkOut": "2026-03-22",
    "guests": 2,
    "totalAmount": 480,
    "status": "pending",
    "createdAt": "2026-03-12T09:45:00Z",
    "notes": "Late check-in requested"
  },
  {
    "id": "BK005",
    "type": "tour",
    "customerName": "David Brown",
    "customerEmail": "david.brown@email.com",
    "customerPhone": "+250 788 567 890",
    "tourId": "gorilla-trekking-volcanoes",
    "tourName": "Gorilla Trekking - Volcanoes National Park",
    "startDate": "2026-04-05",
    "endDate": "2026-04-07",
    "participants": 2,
    "totalAmount": 4290,
    "status": "confirmed",
    "createdAt": "2026-03-11T16:30:00Z",
    "notes": "Celebrating anniversary"
  },
  {
    "id": "BK006",
    "type": "flight",
    "customerName": "Emily Davis",
    "customerEmail": "emily.davis@email.com",
    "customerPhone": "+250 788 678 901",
    "flightDetails": {
      "destination": "Johannesburg",
      "airline": "Kenya Airways",
      "departureDate": "2026-03-28",
      "returnDate": "2026-04-02",
      "passengers": 2,
      "class": "Business"
    },
    "totalAmount": 1794,
    "status": "confirmed",
    "createdAt": "2026-03-09T11:00:00Z",
    "notes": "Business trip"
  },
  {
    "id": "BK007",
    "type": "tour",
    "customerName": "Robert Wilson",
    "customerEmail": "robert.w@email.com",
    "customerPhone": "+250 788 789 012",
    "tourId": "angola-adventure-7-day",
    "tourName": "7-Day Angola Adventure",
    "startDate": "2026-05-10",
    "endDate": "2026-05-16",
    "participants": 3,
    "totalAmount": 5775,
    "status": "pending",
    "createdAt": "2026-03-12T13:20:00Z",
    "notes": "Inquiring about visa requirements"
  },
  {
    "id": "BK008",
    "type": "apartment",
    "customerName": "Lisa Anderson",
    "customerEmail": "lisa.anderson@email.com",
    "customerPhone": "+250 788 890 123",
    "apartmentId": "nyarutarama-modern",
    "apartmentName": "Nyarutarama Modern Studio",
    "checkIn": "2026-03-15",
    "checkOut": "2026-03-29",
    "guests": 1,
    "totalAmount": 1260,
    "status": "confirmed",
    "createdAt": "2026-03-08T15:45:00Z",
    "notes": "Long-term business stay"
  },
  {
    "id": "BK009",
    "type": "flight",
    "customerName": "James Martinez",
    "customerEmail": "james.m@email.com",
    "customerPhone": "+250 788 901 234",
    "flightDetails": {
      "destination": "Nairobi",
      "airline": "RwandAir",
      "departureDate": "2026-03-22",
      "returnDate": "2026-03-24",
      "passengers": 1,
      "class": "Economy"
    },
    "totalAmount": 199,
    "status": "confirmed",
    "createdAt": "2026-03-10T12:30:00Z",
    "notes": "Weekend getaway"
  },
  {
    "id": "BK010",
    "type": "tour",
    "customerName": "Patricia Taylor",
    "customerEmail": "patricia.t@email.com",
    "customerPhone": "+250 788 012 345",
    "tourId": "kigali-full-day",
    "tourName": "Kigali Full-Day City Tour",
    "startDate": "2026-03-16",
    "endDate": "2026-03-16",
    "participants": 2,
    "totalAmount": 160,
    "status": "confirmed",
    "createdAt": "2026-03-12T07:15:00Z",
    "notes": "First time in Rwanda"
  },
  {
    "id": "BK011",
    "type": "tour",
    "customerName": "Christopher Lee",
    "customerEmail": "chris.lee@email.com",
    "customerPhone": "+250 788 123 456",
    "tourId": "akagera-safari-2-day",
    "tourName": "2-Day Akagera National Park Safari",
    "startDate": "2026-04-12",
    "endDate": "2026-04-13",
    "participants": 2,
    "totalAmount": 900,
    "status": "confirmed",
    "createdAt": "2026-03-11T09:00:00Z",
    "notes": "Wildlife photography enthusiasts"
  },
  {
    "id": "BK013",
    "type": "apartment",
    "customerName": "Daniel Harris",
    "customerEmail": "daniel.h@email.com",
    "customerPhone": "+250 788 345 678",
    "apartmentId": "kimihurura-penthouse",
    "apartmentName": "Kimihurura Penthouse Suite",
    "checkIn": "2026-03-20",
    "checkOut": "2026-03-25",
    "guests": 4,
    "totalAmount": 750,
    "status": "confirmed",
    "createdAt": "2026-03-09T16:20:00Z",
    "notes": "Family vacation"
  },
  {
    "id": "BK014",
    "type": "tour",
    "customerName": "Michelle Clark",
    "customerEmail": "michelle.c@email.com",
    "customerPhone": "+250 788 456 789",
    "tourId": "rwanda-3-day-package",
    "tourName": "3-Day Rwanda Package",
    "startDate": "2026-03-30",
    "endDate": "2026-04-01",
    "participants": 2,
    "totalAmount": 1350,
    "status": "confirmed",
    "createdAt": "2026-03-10T10:45:00Z",
    "notes": "Honeymoon trip"
  },
  {
    "id": "BK015",
    "type": "flight",
    "customerName": "Kevin Rodriguez",
    "customerEmail": "kevin.r@email.com",
    "customerPhone": "+250 788 567 890",
    "flightDetails": {
      "destination": "Dubai",
      "airline": "Qatar Airways",
      "departureDate": "2026-04-15",
      "returnDate": "2026-04-22",
      "passengers": 3,
      "class": "Economy"
    },
    "totalAmount": 1797,
    "status": "confirmed",
    "createdAt": "2026-03-08T13:30:00Z",
    "notes": "Family vacation to Dubai"
  },
  {
    "id": "BK016",
    "type": "tour",
    "customerName": "Nancy Lewis",
    "customerEmail": "nancy.lewis@email.com",
    "customerPhone": "+250 788 678 901",
    "tourId": "kigali-half-day",
    "tourName": "Kigali Half-Day City Tour",
    "startDate": "2026-03-14",
    "endDate": "2026-03-14",
    "participants": 1,
    "totalAmount": 60,
    "status": "confirmed",
    "createdAt": "2026-03-12T08:00:00Z",
    "notes": "Layover tour"
  },
  {
    "id": "BK017",
    "type": "apartment",
    "customerName": "Steven Walker",
    "customerEmail": "steven.w@email.com",
    "customerPhone": "+250 788 789 012",
    "apartmentId": "gacuriro-villa",
    "apartmentName": "Gacuriro Executive Villa",
    "checkIn": "2026-04-01",
    "checkOut": "2026-04-15",
    "guests": 6,
    "totalAmount": 2100,
    "status": "pending",
    "createdAt": "2026-03-11T11:15:00Z",
    "notes": "Corporate retreat"
  },
  {
    "id": "BK018",
    "type": "tour",
    "customerName": "Karen Hall",
    "customerEmail": "karen.hall@email.com",
    "customerPhone": "+250 788 890 123",
    "tourId": "zambia-victoria-falls-7-day",
    "tourName": "7-Day Zambia Victoria Falls Adventure",
    "startDate": "2026-05-01",
    "endDate": "2026-05-07",
    "participants": 2,
    "totalAmount": 5760,
    "status": "confirmed",
    "createdAt": "2026-03-09T14:30:00Z",
    "notes": "Adventure seekers"
  },
  {
    "id": "BK019",
    "type": "flight",
    "customerName": "Brian Allen",
    "customerEmail": "brian.allen@email.com",
    "customerPhone": "+250 788 901 234",
    "flightDetails": {
      "destination": "Johannesburg",
      "airline": "Kenya Airways",
      "departureDate": "2026-03-25",
      "returnDate": "2026-03-28",
      "passengers": 1,
      "class": "Economy"
    },
    "totalAmount": 299,
    "status": "confirmed",
    "createdAt": "2026-03-11T15:00:00Z",
    "notes": "Conference attendance"
  },
  {
    "id": "BK020",
    "type": "tour",
    "customerName": "Betty Young",
    "customerEmail": "betty.young@email.com",
    "customerPhone": "+250 788 012 345",
    "tourId": "gorilla-trekking-volcanoes",
    "tourName": "Gorilla Trekking - Volcanoes National Park",
    "startDate": "2026-04-20",
    "endDate": "2026-04-22",
    "participants": 1,
    "totalAmount": 2145,
    "status": "pending",
    "createdAt": "2026-03-12T11:30:00Z",
    "notes": "Solo traveler, wildlife photographer"
  },
  {
    "id": "BK021",
    "type": "apartment",
    "customerName": "George King",
    "customerEmail": "george.king@email.com",
    "customerPhone": "+250 788 123 456",
    "apartmentId": "remera-apartment",
    "apartmentName": "Remera Cozy Apartment",
    "checkIn": "2026-03-17",
    "checkOut": "2026-03-24",
    "guests": 2,
    "totalAmount": 490,
    "status": "confirmed",
    "createdAt": "2026-03-10T09:20:00Z",
    "notes": "Near airport preferred"
  },
  {
    "id": "BK022",
    "type": "tour",
    "customerName": "Dorothy Wright",
    "customerEmail": "dorothy.w@email.com",
    "customerPhone": "+250 788 234 567",
    "tourId": "rwanda-discovery-6-day",
    "tourName": "6-Day Rwanda Discovery Package",
    "startDate": "2026-04-08",
    "endDate": "2026-04-13",
    "participants": 2,
    "totalAmount": 1550,
    "status": "confirmed",
    "createdAt": "2026-03-08T12:00:00Z",
    "notes": "Retirement celebration"
  },
  {
    "id": "BK023",
    "type": "flight",
    "customerName": "Edward Lopez",
    "customerEmail": "edward.lopez@email.com",
    "customerPhone": "+250 788 345 678",
    "flightDetails": {
      "destination": "Nairobi",
      "airline": "RwandAir",
      "departureDate": "2026-03-19",
      "returnDate": "2026-03-21",
      "passengers": 2,
      "class": "Economy"
    },
    "totalAmount": 398,
    "status": "cancelled",
    "createdAt": "2026-03-07T10:30:00Z",
    "notes": "Cancelled due to schedule conflict"
  },
  {
    "id": "BK024",
    "type": "tour",
    "customerName": "Helen Scott",
    "customerEmail": "helen.scott@email.com",
    "customerPhone": "+250 788 456 789",
    "tourId": "akagera-safari-2-day",
    "tourName": "2-Day Akagera National Park Safari",
    "startDate": "2026-03-28",
    "endDate": "2026-03-29",
    "participants": 4,
    "totalAmount": 1800,
    "status": "confirmed",
    "createdAt": "2026-03-11T13:45:00Z",
    "notes": "Group of friends"
  },
  {
    "id": "BK025",
    "type": "apartment",
    "customerName": "Frank Green",
    "customerEmail": "frank.green@email.com",
    "customerPhone": "+250 788 567 890",
    "apartmentId": "kacyiru-loft",
    "apartmentName": "Kacyiru Modern Loft",
    "checkIn": "2026-03-23",
    "checkOut": "2026-04-06",
    "guests": 1,
    "totalAmount": 980,
    "status": "confirmed",
    "createdAt": "2026-03-09T08:30:00Z",
    "notes": "Remote work stay"
  }
]